qwiic_titan_gps.py
sparkfun_qwiic_titan_gps-0.1.1.dist-info/METADATA
sparkfun_qwiic_titan_gps-0.1.1.dist-info/WHEEL
sparkfun_qwiic_titan_gps-0.1.1.dist-info/top_level.txt
sparkfun_qwiic_titan_gps-0.1.1.dist-info/RECORD
